monkeydict/__init__.py
monkeydict-1.0.dist-info/LICENSE
monkeydict-1.0.dist-info/METADATA
monkeydict-1.0.dist-info/WHEEL
monkeydict-1.0.dist-info/top_level.txt
monkeydict-1.0.dist-info/RECORD
