Metadata-Version: 2.1
Name: monkeydict
Version: 1.0
Summary: Access dict values as attributes (works recursively). Fork of EasyDict.
Home-page: https://github.com/cacticouncil/monkeydict
Author: Mathieu Leplatre, Jeremiah Blanchard
Author-email: UNKNOWN
License: LGPL-3.0
Download-URL: http://pypi.python.org/pypi/monkeydict/
Platform: UNKNOWN
Classifier: Topic :: Utilities
Classifier: Natural Language :: English
Classifier: Operating System :: OS Independent
Classifier: Intended Audience :: Developers
Classifier: Development Status :: 5 - Production/Stable
Classifier: License :: OSI Approved :: GNU Lesser General Public License v3 (LGPLv3)
Classifier: Programming Language :: Python :: 3.6
